odoo/addons/product_pricelist_supplierinfo/README.rst
odoo/addons/product_pricelist_supplierinfo/__init__.py
odoo/addons/product_pricelist_supplierinfo/__manifest__.py
odoo/addons/product_pricelist_supplierinfo/i18n/ca.po
odoo/addons/product_pricelist_supplierinfo/i18n/es.po
odoo/addons/product_pricelist_supplierinfo/i18n/fr.po
odoo/addons/product_pricelist_supplierinfo/i18n/it.po
odoo/addons/product_pricelist_supplierinfo/i18n/nl.po
odoo/addons/product_pricelist_supplierinfo/i18n/product_pricelist_supplierinfo.pot
odoo/addons/product_pricelist_supplierinfo/i18n/pt_BR.po
odoo/addons/product_pricelist_supplierinfo/models/__init__.py
odoo/addons/product_pricelist_supplierinfo/models/product_pricelist_item.py
odoo/addons/product_pricelist_supplierinfo/models/product_product.py
odoo/addons/product_pricelist_supplierinfo/models/product_supplierinfo.py
odoo/addons/product_pricelist_supplierinfo/models/product_template.py
odoo/addons/product_pricelist_supplierinfo/readme/CONFIGURE.md
odoo/addons/product_pricelist_supplierinfo/readme/CONTRIBUTORS.md
odoo/addons/product_pricelist_supplierinfo/readme/DESCRIPTION.md
odoo/addons/product_pricelist_supplierinfo/readme/INSTALL.md
odoo/addons/product_pricelist_supplierinfo/readme/ROADMAP.md
odoo/addons/product_pricelist_supplierinfo/readme/USAGE.md
odoo/addons/product_pricelist_supplierinfo/security/res_groups.xml
odoo/addons/product_pricelist_supplierinfo/static/description/icon.png
odoo/addons/product_pricelist_supplierinfo/static/description/index.html
odoo/addons/product_pricelist_supplierinfo/tests/__init__.py
odoo/addons/product_pricelist_supplierinfo/tests/test_product_supplierinfo.py
odoo/addons/product_pricelist_supplierinfo/views/product_pricelist_item_views.xml
odoo/addons/product_pricelist_supplierinfo/views/product_supplierinfo_view.xml
odoo_addon_product_pricelist_supplierinfo-18.0.1.1.0.2.dist-info/METADATA
odoo_addon_product_pricelist_supplierinfo-18.0.1.1.0.2.dist-info/WHEEL
odoo_addon_product_pricelist_supplierinfo-18.0.1.1.0.2.dist-info/top_level.txt
odoo_addon_product_pricelist_supplierinfo-18.0.1.1.0.2.dist-info/RECORD
